source-pipeline/im.v
module im(input [31:2] addr, output [31:0] dout);
    reg [31:0] RAM[127:0];

    assign dout = RAM[addr];
endmodule

source-mc/ctrl_encode_def.v
`timescale 1ns/1ns

// NPC 控制信号：决定下一条 PC 的来源。
`define NPC_PLUS4   3'b000
`define NPC_BRANCH  3'b001
`define NPC_JUMP    3'b010
`define NPC_JALR    3'b100

// 早期 ALU 控制编码，保留兼容用；当前多周期核心主要在 MCCPU.v 中直接译码执行。
`define ALU_NOP   3'b000 
`define ALU_ADD   3'b001
`define ALU_SUB   3'b010 
`define ALU_AND   3'b011
`define ALU_OR    3'b100

// 立即数扩展控制：分别对应 RISC-V 的 I/S/B/U/J 型立即数格式。
`define EXT_CTRL_ITYPE_SHAMT 6'b100000
`define EXT_CTRL_ITYPE	6'b010000
`define EXT_CTRL_STYPE	6'b001000
`define EXT_CTRL_BTYPE	6'b000100
`define EXT_CTRL_UTYPE	6'b000010
`define EXT_CTRL_JTYPE	6'b000001

`define GPRSel_RD 2'b00
`define GPRSel_RT 2'b01
`define GPRSel_31 2'b10

// 寄存器写回数据来源选择。
`define WDSel_FromALU 2'b00
`define WDSel_FromMEM 2'b01
`define WDSel_FromPC 2'b10

// ALU 详细操作编码，由组合 ALU 模块使用；MCCPU.v 中也有等价的函数实现。
`define ALUOp_nop 5'b00000
`define ALUOp_lui 5'b00001
`define ALUOp_auipc 5'b00010
`define ALUOp_add 5'b00011
`define ALUOp_sub 5'b00100
`define ALUOp_bne 5'b00101
`define ALUOp_blt 5'b00110
`define ALUOp_bge 5'b00111
`define ALUOp_bltu 5'b01000
`define ALUOp_bgeu 5'b01001
`define ALUOp_slt 5'b01010
`define ALUOp_sltu 5'b01011
`define ALUOp_xor 5'b01100
`define ALUOp_or 5'b01101
`define ALUOp_and 5'b01110
`define ALUOp_sll 5'b01111
`define ALUOp_srl 5'b10000
`define ALUOp_sra 5'b10001

// 数据存储器访问宽度编码，当前排序程序主要使用 word 访问。
`define dm_word 3'b000
`define dm_halfword 3'b001
`define dm_halfword_unsigned 3'b010
`define dm_byte 3'b011
`define dm_byte_unsigned 3'b100

source-mc/dm.v
`include "ctrl_encode_def.v"
// 数据存储器：128 个 32 位字，供 lw/sw 访问。
module dm(clk, DMWr, addr, din, dout);
   input          clk;
   input          DMWr;
   input  [31:0]  addr;
   input  [31:0]  din;
   output reg [31:0]  dout;
   
   reg [31:0] dmem[127:0];
   
   // 写操作在时钟上升沿发生，符合同步 RAM 的常见写入模型。
   always @(posedge clk)
      if (DMWr) begin
         // addr[8:2] 表示按字寻址；例如 0x180 对应下标 96。
         dmem[addr[8:2]] <= din;
      end
   
     // 读操作为组合读，lw 指令可在同一周期得到 dout。
     always @(*) begin
         dout <= dmem[addr[8:2]];
     end
     
endmodule

source-mc/RF.v
  module RF(   input         clk,
               input         rst,        // 高电平复位
               input         RFWr,       // 寄存器写使能
               input  [4:0]  A1, A2, A3, // A1/A2 为读地址，A3 为写地址
               input  [31:0] WD,         // 写回数据
               output [31:0] RD1, RD2,   // 两个组合读端口
               input  [4:0]  reg_sel,    // 调试选择信号
               output [31:0] reg_data    // 调试输出
           );

    reg [31:0] rf[31:0];
    integer i;

    always @(posedge clk, posedge rst) begin
      if (rst) begin    // 复位时清零 x1-x31，x0 始终保持为 0
        for (i=1; i<32; i=i+1)
            rf[i] <= 0; 
      end
      
      else 
        if (RFWr) begin
          // RISC-V 规定 x0 恒为 0，因此目的寄存器为 x0 时忽略写入。
          if(A3 != 5'b0) begin
              rf[A3] <= WD;
          end
        end
      end

    // 组合读端口；读 x0 时直接返回 0，避免 x0 被数组状态影响。
    assign RD1 = (A1 != 0) ? rf[A1] : 0;
    assign RD2 = (A2 != 0) ? rf[A2] : 0;
    assign reg_data = (reg_sel != 0) ? rf[reg_sel] : 0; 

  endmodule

source-mc/MCCPU.v
`include "ctrl_encode_def.v"

module MCCPU(
    input             clk,
    input             reset,    // 高电平复位
    input      [31:0] inst_in,  // 当前 PC 从指令存储器读出的指令
    input      [31:0] Data_in,  // 数据存储器读出的数据

    output            mem_w,    // 数据存储器写使能，只在 S_MEM_WR 状态有效
    output     [31:0] PC_out,   // 当前取指地址
    output     [31:0] Addr_out, // 数据存储器访问地址
    output     [31:0] Data_out, // 数据存储器写入数据

    input      [4:0]  reg_sel,  // 调试端口：选择观察的寄存器
    output     [31:0] reg_data  // 调试端口：输出选中寄存器的值
    );

    // 多周期 CPU 将一条指令拆成多个状态执行，避免单个周期承担全部组合逻辑。
    localparam S_FETCH  = 3'd0;
    localparam S_DECODE = 3'd1;
    localparam S_EXEC   = 3'd2;
    localparam S_MEM_RD = 3'd3;
    localparam S_MEM_WR = 3'd4;
    localparam S_WB     = 3'd5;

    reg [2:0]  state;       // 当前状态
    reg [31:0] pc;          // PC 寄存器
    reg [31:0] ir;          // 指令寄存器，保存本条指令供后续周期使用
    reg [31:0] aluout_reg;  // ALU/跳转返回地址等执行结果暂存
    reg [31:0] addr_reg;    // 访存地址暂存，供 MEM_RD/MEM_WR 使用
    reg [31:0] wdata_reg;   // sw 写内存数据暂存
    reg [31:0] mdr;         // Memory Data Register，保存 lw 从内存读出的值
    reg [31:0] wd_reg;      // 写回寄存器堆的数据
    reg [4:0]  rd_reg;      // 写回目的寄存器编号
    reg        rf_we_reg;   // 写回阶段的寄存器写使能

    // 所有译码字段都从 ir 取，保证一条指令在多个周期内保持稳定。
    wire [6:0] op     = ir[6:0];
    wire [6:0] funct7 = ir[31:25];
    wire [2:0] funct3 = ir[14:12];
    wire [4:0] rs1    = ir[19:15];
    wire [4:0] rs2    = ir[24:20];
    wire [4:0] rd     = ir[11:7];

    wire [31:0] rd1;
    wire [31:0] rd2;

    // 多周期版本直接在 CPU 内部完成各类立即数扩展。
    wire [31:0] imm_i = {{20{ir[31]}}, ir[31:20]};
    wire [31:0] imm_s = {{20{ir[31]}}, ir[31:25], ir[11:7]};
    wire [31:0] imm_b = {{19{ir[31]}}, ir[31], ir[7], ir[30:25], ir[11:8], 1'b0};
    wire [31:0] imm_u = {ir[31:12], 12'b0};
    wire [31:0] imm_j = {{11{ir[31]}}, ir[31], ir[19:12], ir[20], ir[30:21], 1'b0};

    // 对外连接：PC 送指令存储器，addr/data/mem_w 送数据存储器。
    assign PC_out   = pc;
    assign Addr_out = addr_reg;
    assign Data_out = wdata_reg;
    assign mem_w    = (state == S_MEM_WR);

    // 寄存器堆仍然是双读单写结构；只有 S_WB 状态会拉高 rf_we_reg。
    RF U_RF(
        .clk(clk),
        .rst(reset),
        .RFWr(rf_we_reg),
        .A1(rs1),
        .A2(rs2),
        .A3(rd_reg),
        .WD(wd_reg),
        .RD1(rd1),
        .RD2(rd2),
        .reg_sel(reg_sel),
        .reg_data(reg_data)
    );

    function [31:0] rtype_result;
        input [31:0] a;
        input [31:0] b;
        input [6:0]  f7;
        input [2:0]  f3;
        begin
            // R 型指令的运算由 funct7 + funct3 共同决定。
            // final 中的 slt/sltu 在这里返回 0/1；移位指令只使用 b[4:0]。
            case ({f7, f3})
            {7'b0000000, 3'b000}: rtype_result = a + b;
            {7'b0100000, 3'b000}: rtype_result = a - b;
            {7'b0000000, 3'b010}: rtype_result = ($signed(a) < $signed(b)) ? 32'd1 : 32'd0;
            {7'b0000000, 3'b011}: rtype_result = (a < b) ? 32'd1 : 32'd0;
            {7'b0000000, 3'b100}: rtype_result = a ^ b;
            {7'b0000000, 3'b110}: rtype_result = a | b;
            {7'b0000000, 3'b111}: rtype_result = a & b;
            {7'b0000000, 3'b001}: rtype_result = a << b[4:0];
            {7'b0000000, 3'b101}: rtype_result = a >> b[4:0];
            {7'b0100000, 3'b101}: rtype_result = $signed(a) >>> b[4:0];
            default:              rtype_result = 32'b0;
            endcase
        end
    endfunction

    function [31:0] itype_result;
        input [31:0] a;
        input [31:0] imm;
        input [6:0]  f7;
        input [2:0]  f3;
        begin
            // I 型算术逻辑指令使用 rs1 与符号扩展立即数运算。
            // addi/andi/ori/xori/slti/sltiu/slli/srli/srai 都走本函数。
            // srli 与 srai 都是 funct3=101，通过 funct7 区分是否保留符号位。
            case (f3)
            3'b000: itype_result = a + imm;
            3'b010: itype_result = ($signed(a) < $signed(imm)) ? 32'd1 : 32'd0;
            3'b011: itype_result = (a < imm) ? 32'd1 : 32'd0;
            3'b100: itype_result = a ^ imm;
            3'b110: itype_result = a | imm;
            3'b111: itype_result = a & imm;
            3'b001: itype_result = (f7 == 7'b0000000) ? (a << imm[4:0]) : 32'b0;
            3'b101: itype_result = (f7 == 7'b0100000) ? ($signed(a) >>> imm[4:0]) : (a >> imm[4:0]);
            default: itype_result = 32'b0;
            endcase
        end
    endfunction

    function branch_taken;
        input [31:0] a;
        input [31:0] b;
        input [2:0]  f3;
        begin
            // 分支指令只需要判断条件并更新 PC，不需要写回寄存器。
            // beq/bne 使用相等关系，blt/bge 使用有符号比较，bltu/bgeu 使用无符号比较。
            case (f3)
            3'b000: branch_taken = (a == b);
            3'b001: branch_taken = (a != b);
            3'b100: branch_taken = ($signed(a) < $signed(b));
            3'b101: branch_taken = ($signed(a) >= $signed(b));
            3'b110: branch_taken = (a < b);
            3'b111: branch_taken = (a >= b);
            default: branch_taken = 1'b0;
            endcase
        end
    endfunction

    always @(posedge clk or posedge reset) begin
        if (reset) begin
            // 复位清空所有跨周期寄存器，状态机回到取指状态。
            state      <= S_FETCH;
            pc         <= 32'h0000_0000;
            ir         <= 32'b0;
            aluout_reg <= 32'b0;
            addr_reg   <= 32'b0;
            wdata_reg  <= 32'b0;
            mdr        <= 32'b0;
            wd_reg     <= 32'b0;
            rd_reg     <= 5'b0;
            rf_we_reg  <= 1'b0;
        end else begin
            // 写寄存器只允许在 S_WB 拉高一个周期，因此每拍先默认清 0。
            rf_we_reg <= 1'b0;

            case (state)
            S_FETCH: begin
                // 取指阶段：把当前指令保存到 ir，同时 PC 先顺序加 4。
                // 如果后续发现是 branch/jal，会在 EXEC 阶段修正 PC。
                ir    <= inst_in;
                pc    <= pc + 32'd4;
                state <= S_DECODE;
            end

            S_DECODE: begin
                // 译码阶段目前不做额外寄存，只留出一个周期让寄存器堆读数稳定。
                state <= S_EXEC;
            end

            S_EXEC: begin
                // 执行阶段根据 opcode 决定后续状态：写回、访存或直接回取指。
                rd_reg <= rd;
                case (op)
                7'b0110011: begin // R-type
                    // R 型：两个源操作数来自寄存器堆，结果进入 aluout_reg 等待写回。
                    aluout_reg <= rtype_result(rd1, rd2, funct7, funct3);
                    state <= S_WB;
                end
                7'b0010011: begin // I-type arithmetic
                    // I 型算术逻辑：rs1 与立即数运算，结果写回 rd。
                    // 本状态只计算结果，真正写入寄存器在 S_WB 完成。
                    aluout_reg <= itype_result(rd1, imm_i, funct7, funct3);
                    state <= S_WB;
                end
                7'b0110111: begin // lui
                    // lui：U 型立即数直接作为写回结果。
                    aluout_reg <= imm_u;
                    state <= S_WB;
                end
                7'b0000011: begin // lw
                    // lw：先计算访存地址，下一状态读内存。
                    addr_reg <= rd1 + imm_i;
                    state <= S_MEM_RD;
                end
                7'b0100011: begin // sw
                    // sw：计算地址并锁存写数据，下一状态执行内存写。
                    addr_reg  <= rd1 + imm_s;
                    wdata_reg <= rd2;
                    state <= S_MEM_WR;
                end
                7'b1100011: begin // branch
                    // FETCH 阶段已经 pc+4，因此分支目标用 (pc-4)+imm_b。
                    // 分支指令不进入 S_WB；条件成立时直接修正 PC，然后回到 S_FETCH。
                    if (branch_taken(rd1, rd2, funct3))
                        pc <= (pc - 32'd4) + imm_b;
                    state <= S_FETCH;
                end
                7'b1101111: begin // jal
                    // jal 返回地址为取指后已经更新的 pc，即原 PC+4。
                    // 目标地址从当前指令地址计算，所以使用 (pc-4)+imm_j。
                    aluout_reg <= pc;
                    pc <= (pc - 32'd4) + imm_j;
                    state <= S_WB;
                end
                7'b1100111: begin // jalr
                    // jalr 目标地址由 rs1+imm_i 产生，并按规范清零最低位。
                    // 返回地址仍写入 aluout_reg，若 rd 为 x0，寄存器堆会自动忽略写入。
                    aluout_reg <= pc;
                    pc <= (rd1 + imm_i) & 32'hffff_fffe;
                    state <= S_WB;
                end
                default: begin
                    state <= S_FETCH;
                end
                endcase
            end

            S_MEM_RD: begin
                // 数据存储器组合读出的值锁存到 mdr，下一状态再写回寄存器。
                mdr <= Data_in;
                state <= S_WB;
            end

            S_MEM_WR: begin
                // mem_w 在本状态为 1，数据存储器在该时钟沿完成写入。
                state <= S_FETCH;
            end

            S_WB: begin
                // 写回阶段：lw 写回 mdr，其他需要写回的指令写回 aluout_reg。
                wd_reg <= (op == 7'b0000011) ? mdr : aluout_reg;
                rf_we_reg <= 1'b1;
                state <= S_FETCH;
            end

            default: begin
                state <= S_FETCH;
            end
            endcase
        end
    end

endmodule

source-mc/mccomp.v
module mccomp(clk, rstn, reg_sel, reg_data);
   input          clk, rstn;      // CPU 时钟和复位
   input  [4:0]   reg_sel;        // 调试选择：查看指定寄存器
   output [31:0]  reg_data;       // 调试输出：指定寄存器的值

   wire [31:0] instr;
   wire [31:0] PC;
   wire        MemWrite;
   wire [31:0] dm_addr, dm_din, dm_dout;

   // 多周期 CPU 顶层：输出 PC 取指，输出访存地址/数据控制数据存储器。
   MCCPU U_MCCPU(
      .clk(clk),
      .reset(rstn),
      .inst_in(instr),
      .Data_in(dm_dout),
      .mem_w(MemWrite),
      .PC_out(PC),
      .Addr_out(dm_addr),
      .Data_out(dm_din),
      .reg_sel(reg_sel),
      .reg_data(reg_data)
   );

   // 数据存储器：连接 lw/sw 的地址、写数据、读数据和写使能。
   dm U_DM(
      .clk(clk),
      .DMWr(MemWrite),
      .addr(dm_addr),
      .din(dm_din),
      .dout(dm_dout)
   );

   // 指令存储器按字寻址，因此使用 PC[31:2] 去掉低两位字节偏移。
   im U_imem(
      .addr(PC[31:2]),
      .dout(instr)
   );
endmodule

source-mc/mccomp_tb.v
`timescale 1ns/1ns

module mccomp_tb();
  reg clk;
  reg rstn;
  reg [4:0] reg_sel;
  wire [31:0] reg_data;

  integer errors;
  integer i;

  mccomp dut(.clk(clk), .rstn(rstn), .reg_sel(reg_sel), .reg_data(reg_data));

  initial begin
    $readmemh("rv32_sid_sort_sim.dat", dut.U_imem.RAM, 0, 54);
    for (i = 0; i < 128; i = i + 1) begin
      dut.U_DM.dmem[i] = 32'h0000_0000;
    end

    clk = 1'b1;
    rstn = 1'b1;
    reg_sel = 5'd0;
    errors = 0;
    #10;
    rstn = 1'b0;
  end

  always begin
    #5 clk = ~clk;
  end

  initial begin
    $dumpfile("mccpu_sid_sort.vcd");
    $dumpvars(0, mccomp_tb);

    #25000;

    if (dut.U_DM.dmem[96] !== 32'h5487_3530) begin
      $display("[FAIL] mem[0x180] expected original sid 0x54873530, got %h", dut.U_DM.dmem[96]);
      errors = errors + 1;
    end
    if (dut.U_DM.dmem[97] !== 32'h0334_5578) begin
      $display("[FAIL] mem[0x184] expected sorted sid 0x03345578, got %h", dut.U_DM.dmem[97]);
      errors = errors + 1;
    end
    if (dut.U_MCCPU.U_RF.rf[1] !== 32'hffff_0004) begin
      $display("[FAIL] x1 expected 0xffff0004, got %h", dut.U_MCCPU.U_RF.rf[1]);
      errors = errors + 1;
    end
    if (dut.U_MCCPU.U_RF.rf[2] !== 32'hffff_000c) begin
      $display("[FAIL] x2 expected 0xffff000c, got %h", dut.U_MCCPU.U_RF.rf[2]);
      errors = errors + 1;
    end
    if (dut.U_MCCPU.U_RF.rf[5] !== 32'h0000_0100) begin
      $display("[FAIL] x5 expected 0x00000100, got %h", dut.U_MCCPU.U_RF.rf[5]);
      errors = errors + 1;
    end

    $display("[RESULT] original_sid=%h", dut.U_DM.dmem[96]);
    $display("[RESULT] sorted_sid=%h", dut.U_DM.dmem[97]);

    if (errors == 0)
      $display("[PASS] lab-6 multi-cycle sid sorting simulation passed.");
    else
      $display("[FAIL] lab-6 multi-cycle sid sorting simulation failed with %0d error(s).", errors);

    #20;
    $finish;
  end
endmodule

source-mc/mccpu_sid_sort.vcd
$date
	Wed Jun 17 20:25:39 2026
$end
$version
	Icarus Verilog
$end
$timescale
	1ns
$end
$scope module mccomp_tb $end
$var wire 32 ! reg_data [31:0] $end
$var reg 1 " clk $end
$var reg 5 # reg_sel [4:0] $end
$var reg 1 $ rstn $end
$var integer 32 % errors [31:0] $end
$var integer 32 & i [31:0] $end
$scope module dut $end
$var wire 1 " clk $end
$var wire 5 ' reg_sel [4:0] $end
$var wire 1 $ rstn $end
$var wire 32 ( reg_data [31:0] $end
$var wire 32 ) instr [31:0] $end
$var wire 32 * dm_dout [31:0] $end
$var wire 32 + dm_din [31:0] $end
$var wire 32 , dm_addr [31:0] $end
$var wire 32 - PC [31:0] $end
$var wire 1 . MemWrite $end
$scope module U_DM $end
$var wire 1 " clk $end
$var wire 32 / din [31:0] $end
$var wire 32 0 addr [31:0] $end
$var wire 1 . DMWr $end
$var reg 32 1 dout [31:0] $end
$upscope $end
$scope module U_MCCPU $end
$var wire 32 2 Addr_out [31:0] $end
$var wire 32 3 Data_in [31:0] $end
$var wire 32 4 Data_out [31:0] $end
$var wire 1 " clk $end
$var wire 5 5 reg_sel [4:0] $end
$var wire 1 $ reset $end
$var wire 5 6 rs2 [4:0] $end
$var wire 5 7 rs1 [4:0] $end
$var wire 32 8 reg_data [31:0] $end
$var wire 32 9 rd2 [31:0] $end
$var wire 32 : rd1 [31:0] $end
$var wire 5 ; rd [4:0] $end
$var wire 7 < op [6:0] $end
$var wire 1 . mem_w $end
$var wire 32 = inst_in [31:0] $end
$var wire 32 > imm_u [31:0] $end
$var wire 32 ? imm_s [31:0] $end
$var wire 32 @ imm_j [31:0] $end
$var wire 32 A imm_i [31:0] $end
$var wire 32 B imm_b [31:0] $end
$var wire 7 C funct7 [6:0] $end
$var wire 3 D funct3 [2:0] $end
$var wire 32 E PC_out [31:0] $end
$var reg 32 F addr_reg [31:0] $end
$var reg 32 G aluout_reg [31:0] $end
$var reg 32 H ir [31:0] $end
$var reg 32 I mdr [31:0] $end
$var reg 32 J pc [31:0] $end
$var reg 5 K rd_reg [4:0] $end
$var reg 1 L rf_we_reg $end
$var reg 3 M state [2:0] $end
$var reg 32 N wd_reg [31:0] $end
$var reg 32 O wdata_reg [31:0] $end
$scope function branch_taken $end
$var reg 32 P a [31:0] $end
$var reg 32 Q b [31:0] $end
$var reg 3 R f3 [2:0] $end
$upscope $end
$scope function itype_result $end
$var reg 32 S a [31:0] $end
$var reg 3 T f3 [2:0] $end
$var reg 7 U f7 [6:0] $end
$var reg 32 V imm [31:0] $end
$upscope $end
$scope function rtype_result $end
$var reg 32 W a [31:0] $end
$var reg 32 X b [31:0] $end
$var reg 3 Y f3 [2:0] $end
$var reg 7 Z f7 [6:0] $end
$upscope $end
$scope module U_RF $end
$var wire 5 [ A1 [4:0] $end
$var wire 5 \ A2 [4:0] $end
$var wire 5 ] A3 [4:0] $end
$var wire 1 L RFWr $end
$var wire 32 ^ WD [31:0] $end
$var wire 1 " clk $end
$var wire 5 _ reg_sel [4:0] $end
$var wire 1 $ rst $end
$var wire 32 ` reg_data [31:0] $end
$var wire 32 a RD2 [31:0] $end
$var wire 32 b RD1 [31:0] $end
$var integer 32 c i [31:0] $end
$upscope $end
$upscope $end
$scope module U_imem $end
$var wire 30 d addr [31:2] $end
$var wire 32 e dout [31:0] $end
$upscope $end
$upscope $end
$upscope $end
$enddefinitions $end
#0
$dumpvars
b101010000000000000100010011 e
b0 d
b100000 c
b0 b
b0 a
b0 `
b0 _
b0 ^
b0 ]
b0 \
b0 [
bx Z
bx Y
bx X
bx W
bx V
bx U
bx T
bx S
bx R
bx Q
bx P
b0 O
b0 N
b0 M
0L
b0 K
b0 J
b0 I
b0 H
b0 G
b0 F
b0 E
b0 D
b0 C
b0 B
b0 A
b0 @
b0 ?
b0 >
b101010000000000000100010011 =
b0 <
b0 ;
b0 :
b0 9
b0 8
b0 7
b0 6
b0 5
b0 4
b0 3
b0 2
b0 1
b0 0
b0 /
0.
b0 -
b0 ,
b0 +
b0 *
b101010000000000000100010011 )
b0 (
b0 '
b10000000 &
b0 %
1$
b0 #
1"
b0 !
$end
#5
0"
#10
b100000010001000100010011 )
b100000010001000100010011 =
b100000010001000100010011 e
b1 d
b10011 <
b10 C
b10100 6
b10100 \
b10 ;
b1010100 A
b1000010 ?
b1000010 B
b101010000000000000000000000 >
b1010100 @
b1 M
b100 -
b100 E
b100 J
b101010000000000000100010011 H
1"
0$
#15
0"
#20
b10 M
1"
#25
0"
#30
b101 M
b1010100 G
b10 K
b10 ]
b0 S
b1010100 V
b10 U
b0 T
1"
#35
0"
#40
b0 M
1L
b1010100 N
b1010100 ^
1"
#45
0"
#50
b1010100 :
b1010100 b
b1000011100010000000100010011 )
b1000011100010000000100010011 =
b1000011100010000000100010011 e
b10 d
b0 C
b1 D
b10 7
b10 [
b1000 6
b1000 \
b1000 A
b10 ?
b10 B
b100000010001000000000000 >
b10001000000001000 @
b1 M
b1000 -
b1000 E
b1000 J
b100000010001000100010011 H
0L
1"
#55
0"
#60
b10 M
1"
#65
0"
#70
b101 M
b101010000000000 G
b1010100 S
b1000 V
b0 U
b1 T
1"
#75
0"
#80
b0 M
1L
b101010000000000 N
b101010000000000 ^
1"
#85
0"
#90
b1000000010001000100010011 )
b1000000010001000100010011 =
b1000000010001000100010011 e
b11 d
b100 C
b0 D
b111 6
b111 \
b10000111 A
b10000010 ?
b10000010 B
b1000011100010000000000000000 >
b10000100010000110 @
b101010000000000 :
b101010000000000 b
b1 M
b1100 -
b1100 E
b1100 J
b1000011100010000000100010011 H
0L
1"
#95
0"
#100
b10 M
1"
#105
0"
#110
b101 M
b101010010000111 G
b101010000000000 S
b10000111 V
b100 U
b0 T
1"
#115
0"
#120
b0 M
1L
b101010010000111 N
b101010010000111 ^
1"
#125
0"
#130
b11010100000000000110010011 )
b11010100000000000110010011 =
b11010100000000000110010011 e
b100 d
b0 C
b1 D
b10000 6
b10000 \
b10000 A
b10 ?
b10 B
b1000000010001000000000000 >
b10001000000010000 @
b101010010000111 :
b101010010000111 b
b1 M
b10000 -
b10000 E
b10000 J
b1000000010001000100010011 H
0L
1"
#135
0"
#140
b10 M
1"
#145
0"
#150
b101 M
b1010100100001110000000000000000 G
b101010010000111 S
b10000 V
b0 U
b1 T
1"
#155
0"
#160
b0 M
1L
b1010100100001110000000000000000 N
b1010100100001110000000000000000 ^
1"
#165
0"
#170
b100000011001000110010011 )
b100000011001000110010011 =
b100000011001000110010011 e
b101 d
b1 C
b0 D
b0 7
b0 [
b10101 6
b10101 \
b11 ;
b110101 A
b100011 ?
b100000100010 B
b11010100000000000000000000 >
b100000110100 @
b0 :
b0 b
b1 M
b10100 -
b10100 E
b10100 J
b11010100000000000110010011 H
0L
1"
#175
0"
#180
b10 M
1"
#185
0"
#190
b101 M
b110101 G
b11 K
b11 ]
b0 S
b110101 V
b1 U
b0 T
1"
#195
0"
#200
b0 M
1L
b110101 N
b110101 ^
1"
#205
0"
#210
b110101 :
b110101 b
b11000000011000000110010011 )
b11000000011000000110010011 =
b11000000011000000110010011 e
b110 d
b0 C
b1 D
b11 7
b11 [
b1000 6
b1000 \
b1000 A
b11 ?
b100000000010 B
b100000011001000000000000 >
b11001000000001000 @
b1 M
b11000 -
b11000 E
b11000 J
b100000011001000110010011 H
0L
1"
#215
0"
#220
b10 M
1"
#225
0"
#230
b101 M
b11010100000000 G
b110101 S
b1000 V
b0 U
b1 T
1"
#235
0"
#240
b0 M
1L
b11010100000000 N
b11010100000000 ^
1"
#245
0"
#250
b1100010000000100110011 )
b1100010000000100110011 =
b1100010000000100110011 e
b111 d
b1 C
b0 D
b10000 6
b10000 \
b110000 A
b100011 ?
b100000100010 B
b11000000011000000000000000 >
b11000000000110000 @
b11010100000000 :
b11010100000000 b
b1 M
b11100 -
b11100 E
b11100 J
b11000000011000000110010011 H
0L
1"
#255
0"
#260
b10 M
1"
#265
0"
#270
b101 M
b11010100110000 G
b11010100000000 S
b110000 V
b1 U
b0 T
1"
#275
0"
#280
b0 M
1L
b11010100110000 N
b11010100110000 ^
1"
#285
0"
#290
b11010100110000 9
b11010100110000 a
b11000001000000010000000100011 )
b11000001000000010000000100011 =
b11000001000000010000000100011 e
b1000 d
b110011 <
b0 C
b10 7
b10 [
b11 6
b11 \
b10 ;
b11 A
b10 ?
b10 B
b1100010000000000000000 >
b10000100000000010 @
b1010100100001110000000000000000 :
b1010100100001110000000000000000 b
b1 M
b100000 -
b100000 E
b100000 J
b1100010000000100110011 H
0L
1"
#295
0"
#300
b10 M
1"
#305
0"
#310
b101 M
b1010100100001110011010100110000 G
b10 K
b10 ]
b1010100100001110000000000000000 W
b11010100110000 X
b0 Z
b0 Y
1"
#315
0"
#320
b0 M
1L
b1010100100001110011010100110000 N
b1010100100001110011010100110000 ^
1"
#325
0"
#330
b1010100100001110011010100110000 9
b1010100100001110011010100110000 a
b100000000000010110010011 )
b100000000000010110010011 =
b100000000000010110010011 e
b1001 d
b100011 <
b1100 C
b10 D
b0 7
b0 [
b10 6
b10 \
b0 ;
b110000010 A
b110000000 ?
b110000000 B
b11000001000000010000000000000 >
b10000110000010 @
b0 :
b0 b
b1 M
b100100 -
b100100 E
b100100 J
b11000001000000010000000100011 H
0L
1"
#335
0"
#340
b10 M
1"
#345
0"
#350
1.
b100 M
b1010100100001110011010100110000 +
b1010100100001110011010100110000 /
b1010100100001110011010100110000 4
b1010100100001110011010100110000 O
b110000000 ,
b110000000 0
b110000000 2
b110000000 F
b0 K
b0 ]
1"
#355
0"
#360
b1010100100001110011010100110000 *
b1010100100001110011010100110000 1
b1010100100001110011010100110000 3
0.
b0 M
1"
#365
0"
#370
b0 9
b0 a
b11000000000000010011110000011 )
b11000000000000010011110000011 =
b11000000000000010011110000011 e
b1010 d
b10011 <
b0 C
b0 D
b1000 6
b1000 \
b1011 ;
b1000 A
b1011 ?
b100000001010 B
b100000000000000000000000 >
b1000 @
b1 M
b101000 -
b101000 E
b101000 J
b100000000000010110010011 H
1"
#375
0"
#380
b10 M
1"
#385
0"
#390
b101 M
b1000 G
b1011 K
b1011 ]
b0 S
b1000 V
b0 U
1"
#395
0"
#400
b0 M
1L
b1000 N
b1000 ^
1"
#405
0"
#410
b100110011 )
b100110011 =
b100110011 e
b1011 d
b11 <
b1100 C
b10 D
b0 6
b0 \
b1111 ;
b110000000 A
b110001111 ?
b100110001110 B
b11000000000000010000000000000 >
b10000110000000 @
b1 M
b101100 -
b101100 E
b101100 J
b11000000000000010011110000011 H
0L
1"
#415
0"
#420
b10 M
1"
#425
0"
#430
b11 M
b1111 K
b1111 ]
1"
#435
0"
#440
b101 M
b1010100100001110011010100110000 I
1"
#445
0"
#450
b0 M
1L
b1010100100001110011010100110000 N
b1010100100001110011010100110000 ^
1"
#455
0"
#460
b111100000000001000010011 )
b111100000000001000010011 =
b111100000000001000010011 e
b1100 d
b110011 <
b0 C
b0 D
b10 ;
b0 A
b10 ?
b10 B
b0 >
b0 @
b1 M
b110000 -
b110000 E
b110000 J
b100110011 H
0L
1"
#465
0"
#470
b10 M
1"
#475
0"
#480
b101 M
b0 G
b10 K
b10 ]
b0 W
b0 X
1"
#485
0"
#490
b0 M
1L
b0 N
b0 ^
1"
#495
0"
#500
b1010100100001110011010100110000 9
b1010100100001110011010100110000 a
b10001111111001110110011 )
b10001111111001110110011 =
b10001111111001110110011 e
b1101 d
b10011 <
b1111 6
b1111 \
b100 ;
b1111 A
b100 ?
b100 B
b111100000000000000000000 >
b100000001110 @
b1 M
b110100 -
b110100 E
b110100 J
b111100000000001000010011 H
0L
1"
#505
0"
#510
b10 M
1"
#515
0"
#520
b101 M
b1111 G
b100 K
b100 ]
b1111 V
1"
#525
0"
#530
b0 M
1L
b1111 N
b1111 ^
1"
#535
0"
#540
b1010100100001110011010100110000 :
b1010100100001110011010100110000 b
b1111 9
b1111 a
b1000010001010010010011 )
b1000010001010010010011 =
b1000010001010010010011 e
b1110 d
b110011 <
b111 D
b1111 7
b1111 [
b100 6
b100 \
b111 ;
b100 A
b111 ?
b100000000110 B
b10001111111000000000000 >
b1111111000000000100 @
b1 M
b111000 -
b111000 E
b111000 J
b10001111111001110110011 H
0L
1"
#545
0"
#550
b10 M
1"
#555
0"
#560
b101 M
b0 G
b111 K
b111 ]
b1010100100001110011010100110000 W
b1111 X
b111 Y
1"
#565
0"
#570
b0 M
1L
b0 N
b0 ^
1"
#575
0"
#580
b0 :
b0 b
b0 9
b0 a
b100100111101001110110011 )
b100100111101001110110011 =
b100100111101001110110011 e
b1111 d
b10011 <
b1 D
b10 7
b10 [
b10 6
b10 \
b1001 ;
b10 A
b1001 ?
b100000001000 B
b1000010001000000000000 >
b10001000000000010 @
b1 M
b111100 -
b111100 E
b111100 J
b1000010001010010010011 H
0L
1"
#585
0"
#590
b10 M
1"
#595
0"
#600
b101 M
b1001 K
b1001 ]
b10 V
b1 T
1"
#605
0"
#610
b0 M
1L
1"
#615
0"
#620
b10000100001001010010011 )
b10000100001001010010011 =
b10000100001001010010011 e
b10000 d
b110011 <
b101 D
b111 7
b111 [
b1001 6
b1001 \
b111 ;
b1001 A
b111 ?
b100000000110 B
b100100111101000000000000 >
b111101100000001000 @
b1 M
b1000000 -
b1000000 E
b1000000 J
b100100111101001110110011 H
0L
1"
#625
0"
#630
b10 M
1"
#635
0"
#640
b101 M
b111 K
b111 ]
b0 W
b0 X
b101 Y
1"
#645
0"
#650
b0 M
1L
1"
#655
0"
